c2k.py
cameratokeyboard/__init__.py
cameratokeyboard/args.py
cameratokeyboard/c2kmodel.yml
cameratokeyboard/config.py
cameratokeyboard/logger.py
cameratokeyboard/types.py
cameratokeyboard/app/__init__.py
cameratokeyboard/app/app.py
cameratokeyboard/app/detector.py
cameratokeyboard/app/ui.py
cameratokeyboard/assets/nocam.png
cameratokeyboard/core/__init__.py
cameratokeyboard/core/calibration.py
cameratokeyboard/core/detected_frame.py
cameratokeyboard/core/detected_objects.py
cameratokeyboard/core/finger_down_detector.py
cameratokeyboard/core/math.py
cameratokeyboard/core/keyboard_layouts/__init__.py
cameratokeyboard/core/keyboard_layouts/keyboard_layout.py
cameratokeyboard/core/keyboard_layouts/qwerty.yaml
cameratokeyboard/interfaces/__init__.py
cameratokeyboard/interfaces/calibration_strategy.py
cameratokeyboard/interfaces/detected_frame_data.py
cameratokeyboard/model/__init__.py
cameratokeyboard/model/augmenter.py
cameratokeyboard/model/augmenters.py
cameratokeyboard/model/model_downloader.py
cameratokeyboard/model/partitioner.py
cameratokeyboard/model/train.py
cameratokeyboard/utils/__init__.py
cameratokeyboard/utils/s3_response.py
c2k-0.0.3.dist-info/METADATA
c2k-0.0.3.dist-info/WHEEL
c2k-0.0.3.dist-info/entry_points.txt
c2k-0.0.3.dist-info/licenses/LICENSE-dataset.md
c2k-0.0.3.dist-info/licenses/LICENSE.md
c2k-0.0.3.dist-info/RECORD
