Metadata-Version: 2.3
Name: c2k
Version: 0.0.3
Summary: Acts as a keyboard by looking at your hands!
Project-URL: Homepage, https://github.com/mnvoh/cameratokeyboard
Project-URL: Issues, https://github.com/mnvoh/cameratokeyboard/issues
Author-email: mnvoh <milad@nozary.com>
License-File: LICENSE-dataset.md
License-File: LICENSE.md
Classifier: License :: OSI Approved :: GNU General Public License v3 (GPLv3)
Classifier: Operating System :: OS Independent
Classifier: Programming Language :: Python :: 3
Requires-Python: >=3.8
Requires-Dist: colorlog
Requires-Dist: imgaug
Requires-Dist: numpy
Requires-Dist: opencv-contrib-python
Requires-Dist: pygame-ce
Requires-Dist: pygame-gui
Requires-Dist: pyyaml
Requires-Dist: requests
Requires-Dist: tqdm
Requires-Dist: ultralytics
